llm_sort.py
llm_sort-0.3.dist-info/licenses/LICENSE
llm_sort-0.3.dist-info/METADATA
llm_sort-0.3.dist-info/WHEEL
llm_sort-0.3.dist-info/entry_points.txt
llm_sort-0.3.dist-info/top_level.txt
llm_sort-0.3.dist-info/RECORD
