Metadata-Version: 2.4
Name: llm-sort
Version: 0.3
Summary: LLM plugin for semantic sorting
Author: Evangelos Lamprou
License: Apache-2.0
Project-URL: Homepage, https://github.com/vagos/llm-sort
Project-URL: Changelog, https://github.com/vagos/llm-sort/releases
Project-URL: Issues, https://github.com/vagos/llm-sort/issues
Project-URL: CI, https://github.com/vagos/llm-sort/actions
Classifier: License :: OSI Approved :: Apache Software License
License-File: LICENSE
Requires-Dist: llm>=0.16
Requires-Dist: click!=8.2.1,>=8.0
Provides-Extra: test
Requires-Dist: pytest; extra == "test"
Dynamic: license-file
